pylontech/__init__.py
pylontech/pylontech.py
pylontech/schema.py
pylontech/tools.py
pylontech/transport.py
pylontechpoller/__init__.py
pylontechpoller/poller.py
pylontechpoller/reporter.py
python_pylontech_ext-0.4.5.dist-info/METADATA
python_pylontech_ext-0.4.5.dist-info/WHEEL
python_pylontech_ext-0.4.5.dist-info/entry_points.txt
python_pylontech_ext-0.4.5.dist-info/licenses/LICENSE
python_pylontech_ext-0.4.5.dist-info/RECORD
