Metadata-Version: 2.4
Name: python-pylontech-ext
Version: 0.4.5
Summary: Interfaces with Pylontech Batteries using RS485 protocol
Author-email: Frank Villaro-Dixon <frank@villaro-dixon.eu>, Pavel Shirshov <pshirshov@eml.cc>
License-Expression: MIT
License-File: LICENSE
Keywords: US2000,US2000C,US3000,US5000,lithium battery,pylon,pylontech,rs485
Classifier: Development Status :: 3 - Alpha
Classifier: License :: OSI Approved :: MIT License
Classifier: Topic :: Utilities
Requires-Python: >=3.13
Requires-Dist: construct
Requires-Dist: exscript
Requires-Dist: pymongo
Requires-Dist: pyserial
Requires-Dist: requests
Requires-Dist: rich
Requires-Dist: standard-telnetlib
